[
  {
    "name": "INVOICE_ID",
    "mode": "NULLABLE",
    "type": "INTEGER",
    "description": null,
    "fields": []
  },
  {
    "name": "LAST_UPDATED_BY",
    "mode": "NULLABLE",
    "type": "INTEGER",
    "description": null,
    "fields": []
  },
  {
    "name": "LAST_UPDATE_DATE",
    "mode": "NULLABLE",
    "type": "TIMESTAMP",
    "description": null,
    "fields": []
  },
  {
    "name": "PAYMENT_CROSS_RATE",
    "mode": "NULLABLE",
    "type": "INTEGER",
    "description": null,
    "fields": []
  },
  {
    "name": "PAYMENT_NUM",
    "mode": "NULLABLE",
    "type": "INTEGER",
    "description": null,
    "fields": []
  },
  {
    "name": "AMOUNT_REMAINING",
    "mode": "NULLABLE",
    "type": "FLOAT",
    "description": null,
    "fields": []
  },
  {
    "name": "CREATED_BY",
    "mode": "NULLABLE",
    "type": "INTEGER",
    "description": null,
    "fields": []
  },
  {
    "name": "CREATION_DATE",
    "mode": "NULLABLE",
    "type": "TIMESTAMP",
    "description": null,
    "fields": []
  },
  {
    "name": "DISCOUNT_DATE",
    "mode": "NULLABLE",
    "type": "STRING",
    "description": null,
    "fields": []
  },
  {
    "name": "DUE_DATE",
    "mode": "NULLABLE",
    "type": "STRING",
    "description": null,
    "fields": []
  },
  {
    "name": "FUTURE_PAY_DUE_DATE",
    "mode": "NULLABLE",
    "type": "STRING",
    "description": null,
    "fields": []
  },
  {
    "name": "GROSS_AMOUNT",
    "mode": "NULLABLE",
    "type": "FLOAT",
    "description": null,
    "fields": []
  },
  {
    "name": "HOLD_FLAG",
    "mode": "NULLABLE",
    "type": "BOOLEAN",
    "description": null,
    "fields": []
  },
  {
    "name": "LAST_UPDATE_LOGIN",
    "mode": "NULLABLE",
    "type": "INTEGER",
    "description": null,
    "fields": []
  },
  {
    "name": "PAYMENT_METHOD_LOOKUP_CODE",
    "mode": "NULLABLE",
    "type": "STRING",
    "description": null,
    "fields": []
  },
  {
    "name": "PAYMENT_PRIORITY",
    "mode": "NULLABLE",
    "type": "INTEGER",
    "description": null,
    "fields": []
  },
  {
    "name": "PAYMENT_STATUS_FLAG",
    "mode": "NULLABLE",
    "type": "BOOLEAN",
    "description": null,
    "fields": []
  },
  {
    "name": "SECOND_DISCOUNT_DATE",
    "mode": "NULLABLE",
    "type": "STRING",
    "description": null,
    "fields": []
  },
  {
    "name": "THIRD_DISCOUNT_DATE",
    "mode": "NULLABLE",
    "type": "STRING",
    "description": null,
    "fields": []
  },
  {
    "name": "BATCH_ID",
    "mode": "NULLABLE",
    "type": "STRING",
    "description": null,
    "fields": []
  },
  {
    "name": "DISCOUNT_AMOUNT_AVAILABLE",
    "mode": "NULLABLE",
    "type": "STRING",
    "description": null,
    "fields": []
  },
  {
    "name": "SECOND_DISC_AMT_AVAILABLE",
    "mode": "NULLABLE",
    "type": "STRING",
    "description": null,
    "fields": []
  },
  {
    "name": "THIRD_DISC_AMT_AVAILABLE",
    "mode": "NULLABLE",
    "type": "STRING",
    "description": null,
    "fields": []
  },
  {
    "name": "ATTRIBUTE1",
    "mode": "NULLABLE",
    "type": "STRING",
    "description": null,
    "fields": []
  },
  {
    "name": "ATTRIBUTE10",
    "mode": "NULLABLE",
    "type": "STRING",
    "description": null,
    "fields": []
  },
  {
    "name": "ATTRIBUTE11",
    "mode": "NULLABLE",
    "type": "STRING",
    "description": null,
    "fields": []
  },
  {
    "name": "ATTRIBUTE12",
    "mode": "NULLABLE",
    "type": "STRING",
    "description": null,
    "fields": []
  },
  {
    "name": "ATTRIBUTE13",
    "mode": "NULLABLE",
    "type": "STRING",
    "description": null,
    "fields": []
  },
  {
    "name": "ATTRIBUTE14",
    "mode": "NULLABLE",
    "type": "STRING",
    "description": null,
    "fields": []
  },
  {
    "name": "ATTRIBUTE15",
    "mode": "NULLABLE",
    "type": "STRING",
    "description": null,
    "fields": []
  },
  {
    "name": "ATTRIBUTE2",
    "mode": "NULLABLE",
    "type": "STRING",
    "description": null,
    "fields": []
  },
  {
    "name": "ATTRIBUTE3",
    "mode": "NULLABLE",
    "type": "STRING",
    "description": null,
    "fields": []
  },
  {
    "name": "ATTRIBUTE4",
    "mode": "NULLABLE",
    "type": "STRING",
    "description": null,
    "fields": []
  },
  {
    "name": "ATTRIBUTE5",
    "mode": "NULLABLE",
    "type": "STRING",
    "description": null,
    "fields": []
  },
  {
    "name": "ATTRIBUTE6",
    "mode": "NULLABLE",
    "type": "STRING",
    "description": null,
    "fields": []
  },
  {
    "name": "ATTRIBUTE7",
    "mode": "NULLABLE",
    "type": "STRING",
    "description": null,
    "fields": []
  },
  {
    "name": "ATTRIBUTE8",
    "mode": "NULLABLE",
    "type": "STRING",
    "description": null,
    "fields": []
  },
  {
    "name": "ATTRIBUTE9",
    "mode": "NULLABLE",
    "type": "STRING",
    "description": null,
    "fields": []
  },
  {
    "name": "ATTRIBUTE_CATEGORY",
    "mode": "NULLABLE",
    "type": "STRING",
    "description": null,
    "fields": []
  },
  {
    "name": "DISCOUNT_AMOUNT_REMAINING",
    "mode": "NULLABLE",
    "type": "INTEGER",
    "description": null,
    "fields": []
  },
  {
    "name": "ORG_ID",
    "mode": "NULLABLE",
    "type": "INTEGER",
    "description": null,
    "fields": []
  },
  {
    "name": "GLOBAL_ATTRIBUTE_CATEGORY",
    "mode": "NULLABLE",
    "type": "STRING",
    "description": null,
    "fields": []
  },
  {
    "name": "GLOBAL_ATTRIBUTE1",
    "mode": "NULLABLE",
    "type": "STRING",
    "description": null,
    "fields": []
  },
  {
    "name": "GLOBAL_ATTRIBUTE2",
    "mode": "NULLABLE",
    "type": "STRING",
    "description": null,
    "fields": []
  },
  {
    "name": "GLOBAL_ATTRIBUTE3",
    "mode": "NULLABLE",
    "type": "STRING",
    "description": null,
    "fields": []
  },
  {
    "name": "GLOBAL_ATTRIBUTE4",
    "mode": "NULLABLE",
    "type": "STRING",
    "description": null,
    "fields": []
  },
  {
    "name": "GLOBAL_ATTRIBUTE5",
    "mode": "NULLABLE",
    "type": "STRING",
    "description": null,
    "fields": []
  },
  {
    "name": "GLOBAL_ATTRIBUTE6",
    "mode": "NULLABLE",
    "type": "STRING",
    "description": null,
    "fields": []
  },
  {
    "name": "GLOBAL_ATTRIBUTE7",
    "mode": "NULLABLE",
    "type": "STRING",
    "description": null,
    "fields": []
  },
  {
    "name": "GLOBAL_ATTRIBUTE8",
    "mode": "NULLABLE",
    "type": "BOOLEAN",
    "description": null,
    "fields": []
  },
  {
    "name": "GLOBAL_ATTRIBUTE9",
    "mode": "NULLABLE",
    "type": "STRING",
    "description": null,
    "fields": []
  },
  {
    "name": "GLOBAL_ATTRIBUTE10",
    "mode": "NULLABLE",
    "type": "STRING",
    "description": null,
    "fields": []
  },
  {
    "name": "GLOBAL_ATTRIBUTE11",
    "mode": "NULLABLE",
    "type": "STRING",
    "description": null,
    "fields": []
  },
  {
    "name": "GLOBAL_ATTRIBUTE12",
    "mode": "NULLABLE",
    "type": "STRING",
    "description": null,
    "fields": []
  },
  {
    "name": "GLOBAL_ATTRIBUTE13",
    "mode": "NULLABLE",
    "type": "STRING",
    "description": null,
    "fields": []
  },
  {
    "name": "GLOBAL_ATTRIBUTE14",
    "mode": "NULLABLE",
    "type": "STRING",
    "description": null,
    "fields": []
  },
  {
    "name": "GLOBAL_ATTRIBUTE15",
    "mode": "NULLABLE",
    "type": "STRING",
    "description": null,
    "fields": []
  },
  {
    "name": "GLOBAL_ATTRIBUTE16",
    "mode": "NULLABLE",
    "type": "STRING",
    "description": null,
    "fields": []
  },
  {
    "name": "GLOBAL_ATTRIBUTE17",
    "mode": "NULLABLE",
    "type": "STRING",
    "description": null,
    "fields": []
  },
  {
    "name": "GLOBAL_ATTRIBUTE18",
    "mode": "NULLABLE",
    "type": "STRING",
    "description": null,
    "fields": []
  },
  {
    "name": "GLOBAL_ATTRIBUTE19",
    "mode": "NULLABLE",
    "type": "STRING",
    "description": null,
    "fields": []
  },
  {
    "name": "GLOBAL_ATTRIBUTE20",
    "mode": "NULLABLE",
    "type": "STRING",
    "description": null,
    "fields": []
  },
  {
    "name": "EXTERNAL_BANK_ACCOUNT_ID",
    "mode": "NULLABLE",
    "type": "INTEGER",
    "description": null,
    "fields": []
  },
  {
    "name": "INV_CURR_GROSS_AMOUNT",
    "mode": "NULLABLE",
    "type": "FLOAT",
    "description": null,
    "fields": []
  },
  {
    "name": "CHECKRUN_ID",
    "mode": "NULLABLE",
    "type": "STRING",
    "description": null,
    "fields": []
  },
  {
    "name": "DBI_EVENTS_COMPLETE_FLAG",
    "mode": "NULLABLE",
    "type": "BOOLEAN",
    "description": null,
    "fields": []
  },
  {
    "name": "IBY_HOLD_REASON",
    "mode": "NULLABLE",
    "type": "STRING",
    "description": null,
    "fields": []
  },
  {
    "name": "PAYMENT_METHOD_CODE",
    "mode": "NULLABLE",
    "type": "STRING",
    "description": null,
    "fields": []
  },
  {
    "name": "REMITTANCE_MESSAGE1",
    "mode": "NULLABLE",
    "type": "STRING",
    "description": null,
    "fields": []
  },
  {
    "name": "REMITTANCE_MESSAGE2",
    "mode": "NULLABLE",
    "type": "STRING",
    "description": null,
    "fields": []
  },
  {
    "name": "REMITTANCE_MESSAGE3",
    "mode": "NULLABLE",
    "type": "STRING",
    "description": null,
    "fields": []
  },
  {
    "name": "REMIT_TO_SUPPLIER_NAME",
    "mode": "NULLABLE",
    "type": "STRING",
    "description": null,
    "fields": []
  },
  {
    "name": "REMIT_TO_SUPPLIER_ID",
    "mode": "NULLABLE",
    "type": "STRING",
    "description": null,
    "fields": []
  },
  {
    "name": "REMIT_TO_SUPPLIER_SITE",
    "mode": "NULLABLE",
    "type": "STRING",
    "description": null,
    "fields": []
  },
  {
    "name": "REMIT_TO_SUPPLIER_SITE_ID",
    "mode": "NULLABLE",
    "type": "STRING",
    "description": null,
    "fields": []
  },
  {
    "name": "RELATIONSHIP_ID",
    "mode": "NULLABLE",
    "type": "INTEGER",
    "description": null,
    "fields": []
  }
]